pyfastkron/__init__.py
pyfastkron/fastkronbase.py
pyfastkron/fastkronhandle.py
pyfastkron/fastkronnumpy.py
pyfastkron/fastkrontorch.py
pyfastkron/pywrapper.cpp
pyfastkron/version.py
pyfastkron-1.1.0.dist-info/LICENSE.txt
pyfastkron-1.1.0.dist-info/METADATA
pyfastkron-1.1.0.dist-info/WHEEL
pyfastkron-1.1.0.dist-info/top_level.txt
pyfastkron-1.1.0.dist-info/RECORD
