Metadata-Version: 2.1
Name: pyfastkron
Version: 1.1.0
Summary: A library for efficient matrix and kronecker product matrix multiplication on parallel hardware
Author-email: Abhinav Jangda <abhijangda@gmail.com>
Maintainer-email: Abhinav Jangda <abhijangda@gmail.com>
License: MIT License
Project-URL: Homepage, https://github.com/abhijangda/fastkron
Project-URL: Documentation, https://github.com/abhijangda/fastkron
Project-URL: Repository, https://github.com/abhijangda/fastkron
Keywords: kronecker product,cuda,gpu,kronecker matrix multiplication
Requires-Python: >=3.9
License-File: LICENSE.txt
Requires-Dist: numpy
Requires-Dist: torch
Requires-Dist: torchvision
